syntrac_opentelemetry/instrumentation/langchain/__init__.py
syntrac_opentelemetry/instrumentation/langchain/config.py
syntrac_opentelemetry/instrumentation/langchain/custom_chat_wrapper.py
syntrac_opentelemetry/instrumentation/langchain/custom_llm_wrapper.py
syntrac_opentelemetry/instrumentation/langchain/task_wrapper.py
syntrac_opentelemetry/instrumentation/langchain/utils.py
syntrac_opentelemetry/instrumentation/langchain/version.py
syntrac_opentelemetry/instrumentation/langchain/workflow_wrapper.py
syntrac_opentelemetry_instrumentation_langchain-0.0.4.dist-info/METADATA
syntrac_opentelemetry_instrumentation_langchain-0.0.4.dist-info/WHEEL
syntrac_opentelemetry_instrumentation_langchain-0.0.4.dist-info/entry_points.txt
syntrac_opentelemetry_instrumentation_langchain-0.0.4.dist-info/RECORD
