Metadata-Version: 2.1
Name: syntrac-opentelemetry-instrumentation-langchain
Version: 0.0.4
Summary: OpenTelemetry Langchain instrumentation
Home-page: https://github.com/syntracAI/syntrac/tree/main/packages/python/opentelemetry-instrumentation-langchain
License: Apache-2.0
Author: Vuong Ngo
Author-email: vuongngo.pd@gmail.com
Requires-Python: >=3.9,<4
Classifier: License :: OSI Approved :: Apache Software License
Classifier: Programming Language :: Python :: 3
Classifier: Programming Language :: Python :: 3.9
Classifier: Programming Language :: Python :: 3.10
Classifier: Programming Language :: Python :: 3.11
Classifier: Programming Language :: Python :: 3.12
Provides-Extra: instruments
Requires-Dist: opentelemetry-api (>=1.23.0,<2.0.0)
Requires-Dist: opentelemetry-instrumentation (==0.44b0)
Requires-Dist: opentelemetry-semantic-conventions (==0.44b0)
Requires-Dist: syntrac-opentelemetry-semantic-conventions-ai (==0.0.1)
Project-URL: Repository, https://github.com/syntracAI/syntrac/tree/main/packages/python/opentelemetry-instrumentation-langchain
